{
   "aaData" : [
      {
         "ocurrencias" : 2,
         "query" : "aeropuerto internacional o'hare de chicago tren subterrean"
      },
      {
         "ocurrencias" : 2,
         "query" : "peleas de boxeo del año 1985 de carlos herri"
      },
      {
         "ocurrencias" : 2,
         "query" : "el mejor enganchados d"
      },
      {
         "ocurrencias" : 2,
         "query" : "xombie"
      },
      {
         "ocurrencias" : 2,
         "query" : "fotos de boca juniors"
      },
      {
         "ocurrencias" : 2,
         "query" : "tu recuerdo la voz arg"
      },
      {
         "ocurrencias" : 2,
         "query" : "¿como era la educa"
      },
      {
         "ocurrencias" : 2,
         "query" : "juegos de ju"
      },
      {
         "ocurrencias" : 1,
         "query" : "descargar donkey kong epara pc"
      },
      {
         "ocurrencias" : 3,
         "query" : "como consigo los gorros de paises en mundo gatur"
      },
      {
         "ocurrencias" : 4,
         "query" : "joegus dev"
      },
      {
         "ocurrencias" : 2,
         "query" : "descargar donkey kong en para pc"
      },
      {
         "ocurrencias" : 2,
         "query" : "casi angeles n"
      },
      {
         "ocurrencias" : 3,
         "query" : "mariano paternal en facebook"
      },
      {
         "ocurrencias" : 2,
         "query" : "descargar donkey kong en 3dpara pc"
      },
      {
         "ocurrencias" : 2,
         "query" : "www.merc"
      },
      {
         "ocurrencias" : 1,
         "query" : "minecr"
      },
      {
         "ocurrencias" : 1,
         "query" : "todas las inti"
      },
      {
         "ocurrencias" : 1,
         "query" : "fotos de boc"
      },
      {
         "ocurrencias" : 2,
         "query" : "freddie"
      },
      {
         "ocurrencias" : 2,
         "query" : "todas las intimidades"
      },
      {
         "ocurrencias" : 2,
         "query" : "juegos de juegos,co"
      },
      {
         "ocurrencias" : 2,
         "query" : "de noche mi gatita sa"
      },
      {
         "ocurrencias" : 2,
         "query" : "joegus d"
      },
      {
         "ocurrencias" : 2,
         "query" : "violetta  y  "
      },
      {
         "ocurrencias" : 1,
         "query" : "harry styoes tiene hoyuelos?"
      },
      {
         "ocurrencias" : 2,
         "query" : "ley  educaci0n comun  14"
      },
      {
         "ocurrencias" : 2,
         "query" : "un nene y una que  guarderia de perros"
      },
      {
         "ocurrencias" : 1,
         "query" : "ley  educaci0n comun  "
      },
      {
         "ocurrencias" : 2,
         "query" : "juegos de juegosn"
      },
      {
         "ocurrencias" : 2,
         "query" : "propaganda de desodorante axe 201"
      },
      {
         "ocurrencias" : 3,
         "query" : "juegos tomi dali"
      },
      {
         "ocurrencias" : 2,
         "query" : "ti credo"
      },
      {
         "ocurrencias" : 1,
         "query" : "fotos de boca"
      },
      {
         "ocurrencias" : 2,
         "query" : "descargar donkey kong enpara pc"
      },
      {
         "ocurrencias" : 3,
         "query" : "¿como era la educacion en a"
      },
      {
         "ocurrencias" : 1,
         "query" : "mariz"
      },
      {
         "ocurrencias" : 1,
         "query" : "john cena"
      },
      {
         "ocurrencias" : 2,
         "query" : "www.mercad"
      },
      {
         "ocurrencias" : 1,
         "query" : "reloj pande"
      },
      {
         "ocurrencias" : 2,
         "query" : "todas las intimidades de cody"
      },
      {
         "ocurrencias" : 1,
         "query" : "citroen air cros pak my way 2"
      },
      {
         "ocurrencias" : 2,
         "query" : "que  es  la"
      },
      {
         "ocurrencias" : 2,
         "query" : "¿com"
      },
      {
         "ocurrencias" : 2,
         "query" : "barbie"
      },
      {
         "ocurrencias" : 2,
         "query" : "queen bici"
      },
      {
         "ocurrencias" : 1,
         "query" : "youtu"
      },
      {
         "ocurrencias" : 2,
         "query" : "todas las intimidades de cod"
      },
      {
         "ocurrencias" : 2,
         "query" : "todas las intimidades de cody "
      },
      {
         "ocurrencias" : 2,
         "query" : "tu recuerdo la voz "
      },
      {
         "ocurrencias" : 2,
         "query" : "¿como era la educacion e"
      },
      {
         "ocurrencias" : 2,
         "query" : "como consigo los gorros de paises en mundo gat"
      },
      {
         "ocurrencias" : 2,
         "query" : "informacion sobre el bibli"
      },
      {
         "ocurrencias" : 1,
         "query" : "ley  educaci0n comun  1"
      },
      {
         "ocurrencias" : 2,
         "query" : "junt"
      },
      {
         "ocurrencias" : 2,
         "query" : "fotos de "
      },
      {
         "ocurrencias" : 2,
         "query" : "todas las intimidade"
      },
      {
         "ocurrencias" : 2,
         "query" : "informacion sobre el bi"
      },
      {
         "ocurrencias" : 2,
         "query" : "lapag"
      },
      {
         "ocurrencias" : 2,
         "query" : "informacion sobre el bibl"
      },
      {
         "ocurrencias" : 2,
         "query" : "casi angeles no "
      },
      {
         "ocurrencias" : 2,
         "query" : "ncaa football 12 "
      },
      {
         "ocurrencias" : 2,
         "query" : "aeropuerto internacional o'hare de chicago tren subterreane"
      },
      {
         "ocurrencias" : 2,
         "query" : "jueg"
      },
      {
         "ocurrencias" : 2,
         "query" : "joegus de"
      },
      {
         "ocurrencias" : 1,
         "query" : "mercado libre ropa deportiva nike de nenas"
      },
      {
         "ocurrencias" : 2,
         "query" : "ncaa football 12 f"
      },
      {
         "ocurrencias" : 3,
         "query" : "aeropuerto internacional o'hare de chicago tren subterreaneo"
      },
      {
         "ocurrencias" : 2,
         "query" : "¿como "
      },
      {
         "ocurrencias" : 1,
         "query" : "twitter"
      },
      {
         "ocurrencias" : 2,
         "query" : "juntos som"
      },
      {
         "ocurrencias" : 2,
         "query" : "ti cred"
      },
      {
         "ocurrencias" : 2,
         "query" : "queen "
      },
      {
         "ocurrencias" : 2,
         "query" : "juegos de j"
      },
      {
         "ocurrencias" : 2,
         "query" : "propaganda de desodorante a"
      },
      {
         "ocurrencias" : 1,
         "query" : "juegos friv 3d"
      },
      {
         "ocurrencias" : 2,
         "query" : "como consigo los gorros del mun"
      },
      {
         "ocurrencias" : 2,
         "query" : "el mejor enganchados de "
      },
      {
         "ocurrencias" : 2,
         "query" : "mari"
      },
      {
         "ocurrencias" : 2,
         "query" : "todas las intimidades de "
      },
      {
         "ocurrencias" : 2,
         "query" : "de noche mi gatita s"
      },
      {
         "ocurrencias" : 2,
         "query" : "propaganda de desodorant"
      },
      {
         "ocurrencias" : 2,
         "query" : "¿como era la educ"
      },
      {
         "ocurrencias" : 2,
         "query" : "juegos de jueg"
      },
      {
         "ocurrencias" : 2,
         "query" : "con qué se mide la temperatur"
      },
      {
         "ocurrencias" : 2,
         "query" : "ncaa football 13 franch"
      },
      {
         "ocurrencias" : 2,
         "query" : "informacion sobre el bib"
      },
      {
         "ocurrencias" : 1,
         "query" : "marizela"
      },
      {
         "ocurrencias" : 2,
         "query" : "un nene y una que asen u guarderia de perros"
      },
      {
         "ocurrencias" : 2,
         "query" : "barb"
      },
      {
         "ocurrencias" : 2,
         "query" : "todas las intimidades de co"
      },
      {
         "ocurrencias" : 2,
         "query" : "rimas sobre elo agua"
      },
      {
         "ocurrencias" : 2,
         "query" : "como consigo los gorros del "
      },
      {
         "ocurrencias" : 2,
         "query" : "el mejor enganchados "
      },
      {
         "ocurrencias" : 2,
         "query" : "juntos somos "
      },
      {
         "ocurrencias" : 2,
         "query" : " guarderia de perros"
      },
      {
         "ocurrencias" : 2,
         "query" : "tu recuerdo la voz a"
      },
      {
         "ocurrencias" : 2,
         "query" : "freddie mercury "
      },
      {
         "ocurrencias" : 1,
         "query" : "como consigo los gorros del mundial"
      },
      {
         "ocurrencias" : 1,
         "query" : "mariano paternal en faceboo"
      },
      {
         "ocurrencias" : 1,
         "query" : "octapad roland "
      },
      {
         "ocurrencias" : 2,
         "query" : "todas las intimidades de c"
      },
      {
         "ocurrencias" : 4,
         "query" : "el mejor engancha"
      },
      {
         "ocurrencias" : 2,
         "query" : "freddie mercury ca"
      },
      {
         "ocurrencias" : 1,
         "query" : "#daleboca"
      },
      {
         "ocurrencias" : 2,
         "query" : "simbolos para twitter"
      },
      {
         "ocurrencias" : 2,
         "query" : "como consigo los gorros del mundia"
      },
      {
         "ocurrencias" : 1,
         "query" : "fotos de boca juni"
      },
      {
         "ocurrencias" : 2,
         "query" : "juntos"
      },
      {
         "ocurrencias" : 2,
         "query" : "videos "
      },
      {
         "ocurrencias" : 2,
         "query" : "queen bic"
      },
      {
         "ocurrencias" : 1,
         "query" : "todas las intim"
      },
      {
         "ocurrencias" : 2,
         "query" : "un ne guarderia de perros"
      },
      {
         "ocurrencias" : 2,
         "query" : "de noche mi gatita sale "
      },
      {
         "ocurrencias" : 2,
         "query" : "como consigo los gorros de paises en mundo "
      },
      {
         "ocurrencias" : 2,
         "query" : "un nene y  guarderia de perros"
      },
      {
         "ocurrencias" : 4,
         "query" : "juegos de juegos,com"
      },
      {
         "ocurrencias" : 2,
         "query" : "como consigo los gorros del mu"
      },
      {
         "ocurrencias" : 2,
         "query" : "con qué se mide la temperat"
      },
      {
         "ocurrencias" : 2,
         "query" : "propaganda de desodorante 2"
      },
      {
         "ocurrencias" : 2,
         "query" : "freddie "
      },
      {
         "ocurrencias" : 1,
         "query" : "aeropuerto internacional o'hare de chicago tren subterráneo"
      },
      {
         "ocurrencias" : 2,
         "query" : "de noche m"
      },
      {
         "ocurrencias" : 2,
         "query" : "que  es  lai"
      },
      {
         "ocurrencias" : 2,
         "query" : "fotos de"
      },
      {
         "ocurrencias" : 2,
         "query" : "softo"
      },
      {
         "ocurrencias" : 1,
         "query" : "ley  educaci0n comun "
      },
      {
         "ocurrencias" : 1,
         "query" : "todas las intimidades de cody simp"
      },
      {
         "ocurrencias" : 2,
         "query" : "¿como"
      },
      {
         "ocurrencias" : 2,
         "query" : "¿como er"
      },
      {
         "ocurrencias" : 2,
         "query" : "¿como e"
      },
      {
         "ocurrencias" : 2,
         "query" : "tu recuerdo la voz arge"
      },
      {
         "ocurrencias" : 2,
         "query" : "todas las intimidades "
      },
      {
         "ocurrencias" : 2,
         "query" : "el mejor eng"
      },
      {
         "ocurrencias" : 2,
         "query" : "youn kids malooram"
      },
      {
         "ocurrencias" : 1,
         "query" : "que  es "
      },
      {
         "ocurrencias" : 2,
         "query" : "con qué se mide la p"
      },
      {
         "ocurrencias" : 3,
         "query" : "faceook"
      },
      {
         "ocurrencias" : 2,
         "query" : "ti cre"
      },
      {
         "ocurrencias" : 2,
         "query" : "tu recuerdo l"
      },
      {
         "ocurrencias" : 2,
         "query" : "un nene y una que asen un guarderia de perros"
      },
      {
         "ocurrencias" : 2,
         "query" : "de noche mi gatita "
      },
      {
         "ocurrencias" : 2,
         "query" : "¿como era "
      },
      {
         "ocurrencias" : 2,
         "query" : "ti cr"
      },
      {
         "ocurrencias" : 1,
         "query" : "todas las intimidades de cody simps"
      },
      {
         "ocurrencias" : 2,
         "query" : "casi angeles "
      },
      {
         "ocurrencias" : 2,
         "query" : "fotos de boca juniors "
      },
      {
         "ocurrencias" : 2,
         "query" : "fotos de boca "
      },
      {
         "ocurrencias" : 2,
         "query" : "juegos "
      },
      {
         "ocurrencias" : 2,
         "query" : "youn kids maloo"
      },
      {
         "ocurrencias" : 2,
         "query" : "fred"
      },
      {
         "ocurrencias" : 2,
         "query" : "ncaa football 13 franchise mo"
      },
      {
         "ocurrencias" : 2,
         "query" : "ncaa football 13 f"
      },
      {
         "ocurrencias" : 2,
         "query" : "¿como era l"
      },
      {
         "ocurrencias" : 1,
         "query" : "marize"
      },
      {
         "ocurrencias" : 4,
         "query" : "peleas de boxeo del año 1985 de carlos herr"
      },
      {
         "ocurrencias" : 3,
         "query" : "que  es  laica"
      },
      {
         "ocurrencias" : 2,
         "query" : "xombie 2"
      },
      {
         "ocurrencias" : 2,
         "query" : "el mejor enganchad"
      },
      {
         "ocurrencias" : 2,
         "query" : "tu recuerdo "
      },
      {
         "ocurrencias" : 3,
         "query" : "youtube"
      },
      {
         "ocurrencias" : 2,
         "query" : "todas las intimida"
      },
      {
         "ocurrencias" : 2,
         "query" : "con qué se mide la pres"
      },
      {
         "ocurrencias" : 1,
         "query" : "facebo"
      },
      {
         "ocurrencias" : 2,
         "query" : "propaganda de desodorante 20"
      },
      {
         "ocurrencias" : 2,
         "query" : "el mejor enga"
      },
      {
         "ocurrencias" : 2,
         "query" : "ncaa football 13 franchise "
      },
      {
         "ocurrencias" : 1,
         "query" : "todas las int"
      },
      {
         "ocurrencias" : 2,
         "query" : "juegos de"
      },
      {
         "ocurrencias" : 2,
         "query" : "xombie 2t"
      },
      {
         "ocurrencias" : 2,
         "query" : "television.com.ar"
      },
      {
         "ocurrencias" : 1,
         "query" : "liam payne 2012"
      },
      {
         "ocurrencias" : 2,
         "query" : "queen bi"
      },
      {
         "ocurrencias" : 2,
         "query" : "el mejor engan"
      },
      {
         "ocurrencias" : 2,
         "query" : "queen"
      },
      {
         "ocurrencias" : 2,
         "query" : "violetta  y  n"
      },
      {
         "ocurrencias" : 2,
         "query" : "como consigo los gorros del"
      },
      {
         "ocurrencias" : 2,
         "query" : "ncaa football 12"
      },
      {
         "ocurrencias" : 2,
         "query" : "xombie 2 t"
      },
      {
         "ocurrencias" : 2,
         "query" : "xombie 2 te"
      },
      {
         "ocurrencias" : 2,
         "query" : "queen bicic"
      },
      {
         "ocurrencias" : 2,
         "query" : "¿como era la "
      },
      {
         "ocurrencias" : 2,
         "query" : "queen bicicl"
      },
      {
         "ocurrencias" : 1,
         "query" : "fotos de boca juniors p"
      },
      {
         "ocurrencias" : 2,
         "query" : "quee"
      },
      {
         "ocurrencias" : 1,
         "query" : "descarg"
      },
      {
         "ocurrencias" : 1,
         "query" : "citroen air cros pak my way 201"
      },
      {
         "ocurrencias" : 3,
         "query" : "con qué se mide la presio"
      },
      {
         "ocurrencias" : 1,
         "query" : "foto"
      },
      {
         "ocurrencias" : 2,
         "query" : "lapagina"
      },
      {
         "ocurrencias" : 1,
         "query" : "reloj pandei"
      },
      {
         "ocurrencias" : 2,
         "query" : "lapa"
      },
      {
         "ocurrencias" : 2,
         "query" : "como consigo los gorros de paises en mun"
      },
      {
         "ocurrencias" : 2,
         "query" : "youn kids malo"
      },
      {
         "ocurrencias" : 1,
         "query" : "a que equipo de futbol le dicen fortin"
      },
      {
         "ocurrencias" : 2,
         "query" : "www.me"
      },
      {
         "ocurrencias" : 2,
         "query" : "freddie mer"
      },
      {
         "ocurrencias" : 2,
         "query" : "¿como era la edu"
      },
      {
         "ocurrencias" : 2,
         "query" : "juegos de jue"
      },
      {
         "ocurrencias" : 2,
         "query" : "con qué se mide la pr"
      },
      {
         "ocurrencias" : 1,
         "query" : "citroen air cros pak my way 2011"
      },
      {
         "ocurrencias" : 2,
         "query" : "ti c"
      },
      {
         "ocurrencias" : 2,
         "query" : "xombi"
      },
      {
         "ocurrencias" : 4,
         "query" : "juego"
      },
      {
         "ocurrencias" : 2,
         "query" : "con qué se mide la temper"
      },
      {
         "ocurrencias" : 2,
         "query" : "con qué se mide la presi"
      },
      {
         "ocurrencias" : 2,
         "query" : "juntos somo"
      },
      {
         "ocurrencias" : 2,
         "query" : "¿como era la educacion en"
      },
      {
         "ocurrencias" : 1,
         "query" : "informacion sobre el b"
      },
      {
         "ocurrencias" : 2,
         "query" : "propaganda de desodorante"
      },
      {
         "ocurrencias" : 1,
         "query" : "kcaarg"
      },
      {
         "ocurrencias" : 2,
         "query" : "tu recuerdo la voz argen"
      },
      {
         "ocurrencias" : 1,
         "query" : "imagenes xxx"
      },
      {
         "ocurrencias" : 2,
         "query" : "tu recuerdo la voz ar"
      },
      {
         "ocurrencias" : 1,
         "query" : "ncaa football 12 fran"
      },
      {
         "ocurrencias" : 2,
         "query" : "soft"
      },
      {
         "ocurrencias" : 1,
         "query" : "todas las intimidades de cody sim"
      },
      {
         "ocurrencias" : 2,
         "query" : "ncaa football 12 fr"
      },
      {
         "ocurrencias" : 2,
         "query" : "con qué se mide la te"
      },
      {
         "ocurrencias" : 2,
         "query" : "tu recuerdo la v"
      },
      {
         "ocurrencias" : 2,
         "query" : "con qué se mide la temperatu"
      },
      {
         "ocurrencias" : 2,
         "query" : "www.mer"
      },
      {
         "ocurrencias" : 2,
         "query" : "como consigo los gorros de paises e"
      },
      {
         "ocurrencias" : 2,
         "query" : "el mejor en"
      },
      {
         "ocurrencias" : 2,
         "query" : "¿como era la educacion en "
      },
      {
         "ocurrencias" : 2,
         "query" : "como consigo los gorros de paises en mundo gaturro"
      },
      {
         "ocurrencias" : 2,
         "query" : "juegos de "
      },
      {
         "ocurrencias" : 2,
         "query" : "¿co"
      },
      {
         "ocurrencias" : 1,
         "query" : "fotos de bo"
      },
      {
         "ocurrencias" : 2,
         "query" : "fotos de boca juniors pa"
      },
      {
         "ocurrencias" : 2,
         "query" : "como consigo los gorros del m"
      },
      {
         "ocurrencias" : 2,
         "query" : "juntos so"
      },
      {
         "ocurrencias" : 1,
         "query" : "fotos"
      },
      {
         "ocurrencias" : 2,
         "query" : "¿como era"
      },
      {
         "ocurrencias" : 19,
         "query" : "hebe, marcha"
      },
      {
         "ocurrencias" : 2,
         "query" : "softoni"
      },
      {
         "ocurrencias" : 2,
         "query" : "con qué se mide la tempera"
      },
      {
         "ocurrencias" : 2,
         "query" : "el mejor enganchados de"
      },
      {
         "ocurrencias" : 2,
         "query" : "youn kids maloora"
      },
      {
         "ocurrencias" : 2,
         "query" : "xombie "
      },
      {
         "ocurrencias" : 1,
         "query" : "todas las intimidades de cody s"
      },
      {
         "ocurrencias" : 1,
         "query" : "fotos de boca j"
      },
      {
         "ocurrencias" : 2,
         "query" : "junto"
      },
      {
         "ocurrencias" : 2,
         "query" : "queen b"
      },
      {
         "ocurrencias" : 1,
         "query" : "fredd"
      },
      {
         "ocurrencias" : 2,
         "query" : "www.merca"
      },
      {
         "ocurrencias" : 1,
         "query" : "todas las intimi"
      },
      {
         "ocurrencias" : 2,
         "query" : "como consigo los gorros del mundi"
      },
      {
         "ocurrencias" : 2,
         "query" : "ncaa football 13 franchi"
      },
      {
         "ocurrencias" : 2,
         "query" : "juntos somos"
      },
      {
         "ocurrencias" : 2,
         "query" : "de noche mi gatita"
      },
      {
         "ocurrencias" : 1,
         "query" : "pecositaa y roo"
      },
      {
         "ocurrencias" : 3,
         "query" : "descargar donkey kong en 3d para pc"
      },
      {
         "ocurrencias" : 2,
         "query" : "juegos de juego"
      },
      {
         "ocurrencias" : 2,
         "query" : "lapagin"
      },
      {
         "ocurrencias" : 1,
         "query" : "peinados de trenzas ninas"
      },
      {
         "ocurrencias" : 2,
         "query" : "como consigo los gorros del mund"
      },
      {
         "ocurrencias" : 2,
         "query" : "juegos de juegos,c"
      },
      {
         "ocurrencias" : 2,
         "query" : "lapagi"
      },
      {
         "ocurrencias" : 1,
         "query" : "propaganda de desodorante 2012"
      },
      {
         "ocurrencias" : 2,
         "query" : "todas las intimidades de"
      },
      {
         "ocurrencias" : 2,
         "query" : "softon"
      },
      {
         "ocurrencias" : 2,
         "query" : "lapaginam"
      },
      {
         "ocurrencias" : 2,
         "query" : "freddie me"
      },
      {
         "ocurrencias" : 2,
         "query" : "todas las intimidades de cody simpson"
      },
      {
         "ocurrencias" : 2,
         "query" : "¿como era la e"
      },
      {
         "ocurrencias" : 2,
         "query" : "juntos "
      },
      {
         "ocurrencias" : 1,
         "query" : "todas las intimidades de cody si"
      },
      {
         "ocurrencias" : 2,
         "query" : "ncaa football 13 franchis"
      },
      {
         "ocurrencias" : 2,
         "query" : "vide"
      },
      {
         "ocurrencias" : 2,
         "query" : "joegus devb"
      },
      {
         "ocurrencias" : 2,
         "query" : "tu recuerdo la"
      },
      {
         "ocurrencias" : 2,
         "query" : "http://us.yhs4.search.yahoo.com/yhs/search?fr=altavista"
      },
      {
         "ocurrencias" : 2,
         "query" : "descargar donkey kong en 3para pc"
      },
      {
         "ocurrencias" : 1,
         "query" : "porta "
      },
      {
         "ocurrencias" : 1,
         "query" : "face"
      },
      {
         "ocurrencias" : 2,
         "query" : "freddie mercury c"
      },
      {
         "ocurrencias" : 2,
         "query" : "juegos d"
      },
      {
         "ocurrencias" : 2,
         "query" : "¿como era la ed"
      },
      {
         "ocurrencias" : 2,
         "query" : "ncaa football 13"
      },
      {
         "ocurrencias" : 2,
         "query" : "casi angeles no le"
      },
      {
         "ocurrencias" : 2,
         "query" : "violetta  y"
      },
      {
         "ocurrencias" : 2,
         "query" : "el mejor enganc"
      },
      {
         "ocurrencias" : 2,
         "query" : "facebok"
      },
      {
         "ocurrencias" : 2,
         "query" : "xomb"
      },
      {
         "ocurrencias" : 2,
         "query" : "que  es  laic"
      },
      {
         "ocurrencias" : 2,
         "query" : "fotos de boca junior"
      },
      {
         "ocurrencias" : 2,
         "query" : "como consigo los gorros d"
      },
      {
         "ocurrencias" : 1,
         "query" : "fotos de b"
      },
      {
         "ocurrencias" : 2,
         "query" : "mercadolibre"
      },
      {
         "ocurrencias" : 4,
         "query" : "casi angeles no l"
      },
      {
         "ocurrencias" : 2,
         "query" : "ncaa football 13 franchise m"
      },
      {
         "ocurrencias" : 2,
         "query" : "youn kids maloor"
      },
      {
         "ocurrencias" : 2,
         "query" : "un nene y una q guarderia de perros"
      },
      {
         "ocurrencias" : 2,
         "query" : "ncaa football 1"
      },
      {
         "ocurrencias" : 2,
         "query" : "propaganda de desodorante axe 20"
      },
      {
         "ocurrencias" : 4,
         "query" : "como consigo los gorros de paises en mundo gaturr"
      },
      {
         "ocurrencias" : 2,
         "query" : "casi angeles no"
      },
      {
         "ocurrencias" : 1,
         "query" : "descar"
      },
      {
         "ocurrencias" : 2,
         "query" : "juegos de juegos"
      },
      {
         "ocurrencias" : 2,
         "query" : "mapa de europa "
      },
      {
         "ocurrencias" : 1,
         "query" : "todas las in"
      },
      {
         "ocurrencias" : 4,
         "query" : "propaganda de desodorante "
      },
      {
         "ocurrencias" : 2,
         "query" : "tu recuerdo la voz"
      },
      {
         "ocurrencias" : 2,
         "query" : "juegos de juegos,"
      },
      {
         "ocurrencias" : 2,
         "query" : "como consigo los gorros de pai"
      },
      {
         "ocurrencias" : 2,
         "query" : "mercadolib"
      },
      {
         "ocurrencias" : 2,
         "query" : "que  es  l"
      },
      {
         "ocurrencias" : 2,
         "query" : "propaganda de desodorante 201"
      },
      {
         "ocurrencias" : 1,
         "query" : "todas las"
      },
      {
         "ocurrencias" : 1,
         "query" : "tu recuerdo la voz argent"
      },
      {
         "ocurrencias" : 1,
         "query" : "que es glucosa"
      },
      {
         "ocurrencias" : 2,
         "query" : "ncaa football 12 fra"
      },
      {
         "ocurrencias" : 2,
         "query" : "¿como era la"
      },
      {
         "ocurrencias" : 2,
         "query" : "todas las intimidades d"
      },
      {
         "ocurrencias" : 2,
         "query" : "freddie mercury cam"
      },
      {
         "ocurrencias" : 1,
         "query" : "que  es  "
      },
      {
         "ocurrencias" : 2,
         "query" : "juegoso"
      },
      {
         "ocurrencias" : 2,
         "query" : "propaganda de desodorante axe"
      },
      {
         "ocurrencias" : 2,
         "query" : "de noche mi gatit"
      },
      {
         "ocurrencias" : 1,
         "query" : "citroen air cros pak my way "
      },
      {
         "ocurrencias" : 2,
         "query" : "xombie 2 "
      },
      {
         "ocurrencias" : 1,
         "query" : "citroen air cros pak my way 20"
      },
      {
         "ocurrencias" : 2,
         "query" : "www.m"
      },
      {
         "ocurrencias" : 2,
         "query" : "juntos s"
      },
      {
         "ocurrencias" : 2,
         "query" : "como consigo los gorros de"
      },
      {
         "ocurrencias" : 1,
         "query" : "fotos de boca jun"
      },
      {
         "ocurrencias" : 2,
         "query" : "aeropuerto internacional o'hare de chicago tren subterrea"
      },
      {
         "ocurrencias" : 2,
         "query" : "un nene y una que ase guarderia de perros"
      },
      {
         "ocurrencias" : 1,
         "query" : "todas las intimid"
      },
      {
         "ocurrencias" : 3,
         "query" : "todos los juegos de cusco"
      },
      {
         "ocurrencias" : 2,
         "query" : "tu recuerdo la "
      },
      {
         "ocurrencias" : 2,
         "query" : "con qué se mide la tempe"
      },
      {
         "ocurrencias" : 2,
         "query" : "el mejor enganchados"
      },
      {
         "ocurrencias" : 1,
         "query" : "todas las i"
      },
      {
         "ocurrencias" : 2,
         "query" : "tu recuerdo la vo"
      },
      {
         "ocurrencias" : 2,
         "query" : "con qué se mide la pre"
      },
      {
         "ocurrencias" : 2,
         "query" : "videos"
      },
      {
         "ocurrencias" : 2,
         "query" : "que sucede  en nuestro pais con el implante cloquial"
      },
      {
         "ocurrencias" : 2,
         "query" : "todas las intimidad"
      },
      {
         "ocurrencias" : 1,
         "query" : "yout"
      },
      {
         "ocurrencias" : 2,
         "query" : "ncaa football 13 franchise mod"
      },
      {
         "ocurrencias" : 2,
         "query" : "tu recuerdo"
      },
      {
         "ocurrencias" : 1,
         "query" : "pixxx.com"
      }
   ]
}
